{
    "items": [
      {
        "sys": { "id": "1" },
        "fields": {
          "title": "Whitenbar",
          "price": 850.01,
          "image": { "fields": { "file": { "url": "https://s7d5.scene7.com/is/image/Anthropologie/61069209-1135-CH0097_b?$a15-mto-carousel$&hei=640&qlt=80&fit=constrain" } } }
        }
      },
      {
        "sys": { "id": "2" },
        "fields": {
          "title": "king panel bed",
          "price": 12.99,
          "image": { "fields": { "file": { "url": "https://s7d5.scene7.com/is/image/Anthropologie/62166434-4108-L-WL0023-WFRG_b?$a15-mto-carousel$&hei=640&qlt=80&fit=constrain" } } }
        }
      },
      {
        "sys": { "id": "3" },
        "fields": {
          "title": "Single panel bed",
          "price": 12.99,
          "image": { "fields": { "file": { "url": "./carrtimages/product-3.jpeg" } } }
        }
      },
      {
        "sys": { "id": "4" },
        "fields": {
          "title": "twin panel bed",
          "price": 22.99,
          "image": { "fields": { "file": { "url": "./carrtimages/product-4.jpeg" } } }
        }
      },
      {
        "sys": { "id": "5" },
        "fields": {
          "title": "fridge",
          "price": 88.99,
          "image": { "fields": { "file": { "url": "./carrtimages/product-5.jpeg" } } }
        }
      },
      {
        "sys": { "id": "6" },
        "fields": {
          "title": "dresser",
          "price": 32.99,
          "image": { "fields": { "file": { "url": "./carrtimages/product-6.jpeg" } } }
        }
      },
      {
        "sys": { "id": "7" },
        "fields": {
          "title": "couch",
          "price": 45.99,
          "image": { "fields": { "file": { "url": "./carrtimages/product-7.jpeg" } } }
        }
      },
      {
        "sys": { "id": "8" },
        "fields": {
          "title": "table",
          "price": 33.99,
          "image": { "fields": { "file": { "url": "./carrtimages/product-8.jpeg" } } }
        }
      }
    ]
  }
  